{
  "book": "numbers",
  "parasha": "behaalotcha",
  "chapter": 11,
  "verse": 12,
  "hebrew": [
    "[placeholder_word_12_1]",
    "[placeholder_word_12_2]",
    "[placeholder_word_12_3]"
  ],
  "words": [
    {
      "hebrew": "[placeholder_word_12_1]",
      "transliteration": "placeholder_12_1",
      "translations": [
        {
          "meaning": "[перевод слова 12_1]",
          "context": "[контекст для слова 12_1]",
          "frequency": "common"
        }
      ]
    },
    {
      "hebrew": "[placeholder_word_12_2]",
      "transliteration": "placeholder_12_2",
      "translations": [
        {
          "meaning": "[перевод слова 12_2]",
          "context": "[контекст для слова 12_2]",
          "frequency": "common"
        }
      ]
    },
    {
      "hebrew": "[placeholder_word_12_3]",
      "transliteration": "placeholder_12_3",
      "translations": [
        {
          "meaning": "[перевод слова 12_3]",
          "context": "[контекст для слова 12_3]",
          "frequency": "common"
        }
      ]
    }
  ],
  "commentaries": {
    "rashi": "[Комментарий Раши на стих 11:12]",
    "ramban": "[Комментарий Рамбана на стих 11:12]"
  },
  "metadata": {
    "lastUpdated": "2025-08-04T20:47:56.915Z",
    "dataVersion": "3.0.0",
    "completeness": {
      "words": "placeholder",
      "translations": "placeholder",
      "commentaries": "placeholder"
    }
  }
}